agentsystems_toolkit/__init__.py
agentsystems_toolkit/progress_tracker.py
agentsystems_toolkit/licenses/python/ATTRIBUTIONS.md
agentsystems_toolkit/licenses/python/THIRD_PARTY_LICENSES.json
agentsystems_toolkit/licenses/python/THIRD_PARTY_REQUIREMENTS.txt
agentsystems_toolkit/models/__init__.py
agentsystems_toolkit/models/langchain.py
agentsystems_toolkit/models/router.py
agentsystems_toolkit-0.2.1.dist-info/licenses/LICENSE
agentsystems_toolkit-0.2.1.dist-info/METADATA
agentsystems_toolkit-0.2.1.dist-info/WHEEL
agentsystems_toolkit-0.2.1.dist-info/top_level.txt
agentsystems_toolkit-0.2.1.dist-info/RECORD
