Metadata-Version: 2.4
Name: agentsystems-toolkit
Version: 0.2.1
Summary: Development toolkit for building AgentSystems agents
Author-email: AgentSystems <support@agentsystems.ai>
License-Expression: Apache-2.0
Requires-Python: >=3.11
License-File: LICENSE
Requires-Dist: PyYAML>=6.0
Requires-Dist: pydantic>=2.0
Requires-Dist: requests>=2.31.0
Provides-Extra: langchain
Requires-Dist: langchain-core>=0.1.0; extra == "langchain"
Requires-Dist: langchain-anthropic>=0.1.0; extra == "langchain"
Requires-Dist: langchain-openai>=0.1.0; extra == "langchain"
Requires-Dist: langchain-aws>=0.1.0; extra == "langchain"
Requires-Dist: langchain-ollama>=0.1.0; extra == "langchain"
Provides-Extra: dev
Requires-Dist: pytest>=7.0; extra == "dev"
Requires-Dist: pytest-cov>=4.0; extra == "dev"
Requires-Dist: black>=23.0; extra == "dev"
Requires-Dist: ruff>=0.1.0; extra == "dev"
Requires-Dist: mypy>=1.5; extra == "dev"
Requires-Dist: types-requests>=2.31.0; extra == "dev"
Provides-Extra: license-files
Requires-Dist: LICENSE; extra == "license-files"
Dynamic: license-file
